{
	"id": "4b282e10-beee-4894-92b3-47adaf26b46d",
	"name": "StartIT_variables",
	"values": [
		{
			"key": "token",
			"value": "eyJhbGciOiJIUzI1NiIsInR5cCI6IkpXVCJ9.eyJuYW1laWQiOiIxIiwidW5pcXVlX25hbWUiOiJhZG1pbiIsInJvbGUiOiJBZG1pbmlzdHJhdG9yIiwibmJmIjoxNTgyMjIxMTU3LCJleHAiOjE1ODIzMDc1NTcsImlhdCI6MTU4MjIyMTE1N30.913fSNbgmBfI8x5Q-jYyyYgN0HHVQsbXUI5E86sM1-8",
			"enabled": true
		},
		{
			"key": "newNationality",
			"value": "MG_1582221158687",
			"enabled": true
		},
		{
			"key": "newNationalityId",
			"value": "8847",
			"enabled": true
		},
		{
			"key": "changedNationality",
			"value": "MG_1582221159561",
			"enabled": true
		},
		{
			"key": "username",
			"value": "admin",
			"enabled": true
		},
		{
			"key": "password",
			"value": "admin",
			"enabled": true
		}
	],
	"_postman_variable_scope": "environment",
	"_postman_exported_at": "2020-02-20T18:24:34.894Z",
	"_postman_exported_using": "Postman/7.18.1"
}